LICENSE
MANIFEST.in
README.md
setup.cfg
setup.py
zenrpc/__init__.py
zenrpc.egg-info/PKG-INFO
zenrpc.egg-info/SOURCES.txt
zenrpc.egg-info/dependency_links.txt
zenrpc.egg-info/requires.txt
zenrpc.egg-info/top_level.txt
zenrpc/asy/ConnectionRemote.py
zenrpc/asy/RPC_Client.py
zenrpc/asy/RPC_Server.py
zenrpc/asy/Responser.py
zenrpc/asy/__init__.py
zenrpc/syn/ConnectionRemote.py
zenrpc/syn/RPC_Client.py
zenrpc/syn/RPC_Server.py
zenrpc/syn/Responser.py
zenrpc/syn/__init__.py