Metadata-Version: 2.4
Name: zenrpc
Version: 1.0.0
Summary: Json RPC Python server-client class syn and async
Home-page: https://github.com/EduardoPagotto/zenrpc.git
Author: Eduardo Pagotto
Author-email: edupagotto@gmail.com
License: MIT License
Platform: any
Classifier: Intended Audience :: Developers
Classifier: Topic :: File Formats :: JSON
Classifier: Topic :: Software Development :: Libraries
Classifier: Programming Language :: Python :: 3
Classifier: Operating System :: OS Independent
License-File: LICENSE
Requires-Dist: setuptools
Requires-Dist: typing_extensions
Requires-Dist: wheel
Requires-Dist: zencomm
Requires-Dist: sjsonrpc
Dynamic: author
Dynamic: author-email
Dynamic: classifier
Dynamic: description
Dynamic: description-content-type
Dynamic: home-page
Dynamic: license
Dynamic: license-file
Dynamic: platform
Dynamic: requires-dist
Dynamic: summary
